setup.py
myadipkg/__init__.py
myadipkg/calculator.py
myadipkg.egg-info/PKG-INFO
myadipkg.egg-info/SOURCES.txt
myadipkg.egg-info/dependency_links.txt
myadipkg.egg-info/top_level.txt