Metadata-Version: 2.1
Name: myadipkg
Version: 0.0.1
Summary: pooja"s ADI python package module
Home-page: https://github.com/hkshitesh/mydemopackage
Author: pagarwa3
Author-email: poojaag1606@gmail.com
License: UNKNOWN
Platform: UNKNOWN
Classifier: Programming Language :: Python :: 3
Classifier: Operating System :: OS Independent
